absgd/__init__.py
absgd/datasets/__init__.py
absgd/datasets/imblanacedCIFAR.py
absgd/evaluations/__init__.py
absgd/losses/ABLosses.py
absgd/losses/__init__.py
absgd/optimizers/ABoptimizers.py
absgd/optimizers/__init__.py
absgd-0.0.1.dist-info/LICENSE
absgd-0.0.1.dist-info/METADATA
absgd-0.0.1.dist-info/WHEEL
absgd-0.0.1.dist-info/top_level.txt
absgd-0.0.1.dist-info/RECORD
