Metadata-Version: 2.1
Name: absgd
Version: 0.0.1
Summary: The package for ABSGD
Author-email: Qi Qi <qqi7@uiowa.edu>
Project-URL: Homepage, https://github.com/qiqi-helloworld/
Project-URL: Bug Tracker, https://github.com/qiqi-helloworld/
Classifier: Programming Language :: Python :: 3
Classifier: License :: OSI Approved :: MIT License
Classifier: Operating System :: OS Independent
Requires-Python: >=3.6
License-File: LICENSE
